[{
        "_id": "672602ef0ed5d7acd28bb30b",
        "name": "Apartament_1",
        "image": "https://i.ibb.co/1q6TT6j/women-on-yoga-2021-08-26-15-44-27-utc.jpg",
        "numberofrooms": 3,
        "price": "200",
        "description": "Acest apartament are conditii destul de bune si o amplasare langa centrul orasului.",
        "ownername": "Popescu Alexandru",
        "owneremail": "popescu@alex.com",
        "status": "disponibil",
        "totalbooked": 9,
        "location": "Timisoara, str Daliei",
        "reason": null
    },
    {
        "_id": "672602ef0ed5d7acd28bb30c",
        "name": "Apartament_2",
        "image": "https://i.ibb.co/1q6TT6j/women-on-yoga-2021-08-26-15-44-27-utc.jpg",
        "numberofrooms": 2,
        "price": "150",
        "description": "Acest apartament are conditii destul de bune si o amplasare langa centrul orasului.",
        "ownername": "Serban Marian",
        "owneremail": "serban@marian.com",
        "status": "disponibil",
        "totalbooked": 3,
        "location": "Timisoara, str Eroilor de la Tisa",
        "reason": null
    },
    {
        "_id": "672602ef0ed5d7acd28bb30d",
        "name": "Apartament - 3",
        "image": "poza3.jpg",
        "numberofrooms": 4,
        "price": "400",
        "description": "Acest apartament are conditii destul de bune si o amplasare langa centrul orasului!",
        "ownername": "Grigorescu Maria",
        "owneremail": "grigorescu@maria.com",
        "status": "disponibil",
        "totalbooked": 5,
        "location": "Timisoara, strada Daliei",
        "reason": null
    }
]